{
  "title": "إضافة متغير رقم العينة",
  "navigation": "إضافة رقم العينة",
  "sampleSize": "حدد حجم العينات (على سبيل المثال، 5)",
  "sampleVarName": "حدد اسم متغير العينة الذي تريد إضافته (على سبيل المثال، sample). إذا كان اسم المتغير موجودًا بالفعل في مجموعة البيانات، فسيتم تحديثه",
  "help": {
    "title": "إضافة متغير لتحديد رقم العينة",
    "body": "\n\t\t\t\t<b>الوصف</b></br>\n\t\t\t\tأضف متغير رقم العينة (أي عمود) إلى مجموعة البيانات لحجم عينة محدد لاستخدام رقم العينة لتجميع البيانات لتحليل البيانات في المستقبل\n\t\t\t\t<br/>\n\t\t\t\t<br/>\n\t\t\t\tيحتاج متغير رقم العينة في مجموعة البيانات إلى إجراء العديد من التحليلات مثل قدرة العملية، ومخططات شيوارت مثل xbar و R و S، إلخ\n\t\t\t\t<br/>\n\t\t\t\t<br/>\n\t\t\t"
  }
}