{
  "title": "تطبيق دالة على جميع صفوف المتغيرات المحددة.",
  "navigation": "تطبيق دالة على الصفوف",
  "label1": "إنشاء متغير جديد أو الكتابة فوق متغير موجود عن طريق تطبيق دالة على جميع قيم الصفوف للمتغيرات المحددة.",
  "newvar": "أدخل متغيرًا جديدًا/اكتب فوق متغير موجود",
  "target": "حدد المتغيرات",
  "selectctrl": "اختر عملية للتطبيق",
  "help": {
    "title": "تطبيق دالة",
    "r_help": "help(apply,package='base')",
    "body": "\n<b>الوصف</b></br>\nتطبق دالة عبر جميع صفوف المتغيرات المحددة (الأعمدة) في مجموعة البيانات. نستخدم دالة select ومشغل الأنابيب ( %>% ) من حزمة dplyr لاختيار المتغيرات التي سنطبق عليها دالة. (تتم تمرير هذه المتغيرات إلى دالة apply)\n<br/>\n<b>الاستخدام</b>\n<br/>\n<code> \ndataset_name$new_variable <-dataset_name  %>% select(var1,var2) %>% apply(1, function_name, na.rm = TRUE)\napply(X, MARGIN, FUN, ...)\n</code> <br/>\n<b>المعلمات</b><br/>\n<ul>\n<li>\nX: مصفوفة تشمل مصفوفة. يتم تمرير المتغيرات المحددة عبر dplyr\n</li>\n<li>\nMARGIN: متجه يعطي الفهارس التي ستطبق عليها الدالة. على سبيل المثال، لمصفوفة 1 تشير إلى الصفوف، 2 تشير إلى الأعمدة، c(1, 2) تشير إلى الصفوف والأعمدة. حيث\nX لديها أسماء أبعاد مسماة، يمكن أن تكون متجه حرفي يختار أسماء الأبعاد. مجموعة البيانات التي تحتوي على المتغير var\n</li>\n<li>\nFUN: الدالة التي سيتم تطبيقها\n</li>\n</ul>\n<b>القيمة</b><br/>\nالقيم المحسوبة مخزنة مباشرة في مجموعة البيانات\n<b>الحزمة</b></br>\ndplyr</br>\n<b>المساعدة</b></br>\nhelp(apply)\n"
  }
}