{
  "title": "عينة من توزيع F",
  "navigation": "عينة من توزيع F",
  "entrdsname": "أدخل اسم مجموعة البيانات",
  "dfnumerator": "درجات الحرية للمقام",
  "dfdenominator": "درجات الحرية للمؤشر",
  "lblnoofsamples": "عدد العينات (الصفوف)",
  "lblnoofobsv": "عدد الملاحظات (الأعمدة)",
  "lblseed": "البذور",
  "lblAddtoDS": "إضافة إلى مجموعة البيانات",
  "chklbl1": "متوسطات العينة",
  "chklbl2": "مجموعات العينة",
  "chklbl3": "الانحرافات المعيارية للعينة",
  "help": {
    "title": "عينة من توزيع F",
    "r_help": "help(rf, package=stats)",
    "body": "\n            ​​\n            <b>الوصف</b>\n            <br/>\n            الكثافة، دالة التوزيع، دالة الكمية والتوليد العشوائي لتوزيع F مع df1 و df2 درجات الحرية (ومعامل عدم المركزية الاختياري ncp).\n            <br/>\n            <b>الاستخدام</b>\n            <br/>\n            <code>\n                df(x, df1, df2, ncp, log = FALSE)\n                <br/>\n                pf(q, df1, df2, ncp, lower.tail = TRUE, log.p = FALSE)\n                <br/>\n                qf(p, df1, df2, ncp, lower.tail = TRUE, log.p = FALSE)\n                <br/>\n                rf(n, df1, df2, ncp)\n                <br/>\n            </code>\n            <br/>\n            <b>المعلمات</b>\n            <br/>\n            <ul>\n                <li>x, q : متجه من الكميات.</li>\n                \n                \n                <li>p : متجه من الاحتمالات.</li>\n                \n                \n                <li>n : عدد الملاحظات. إذا كانت length(n) > 1، يتم أخذ الطول ليكون العدد المطلوب.</li>\n                \n                \n                <li>df1، df2 : درجات الحرية. يُسمح بـ Inf.</li>\n                \n                \n                <li>ncp : معامل عدم المركزية. إذا تم حذفه، يُفترض أن توزيع F مركزي.</li>\n                \n                \n                <li>log، log.p : منطقي؛ إذا كان TRUE، يتم إعطاء الاحتمالات p كـ log(p).</li>\n                \n                \n                <li>lower.tail : منطقي؛ إذا كان TRUE (افتراضي)، فإن الاحتمالات هي P[X ≤ x]، وإلا، P[X > x].</li>\n            </ul>\n            \n            \n            \n            <br/>\n            <b>التفاصيل</b>\n            <br/>\n            توزيع F مع df1 = n1 و df2 = n2 درجات الحرية له كثافة\n            <br/>\n            <code>f(x) = Γ((n1 + n2)/2) / (Γ(n1/2) Γ(n2/2)) (n1/n2)^(n1/2) x^(n1/2 - 1) (1 + (n1/n2) x)^-(n1 + n2)/2</code>\n            <br/>\n            لـ x > 0.\n            <br/>\n            إنه توزيع نسبة متوسط المربعات لـ n1 و n2 من المعايير المستقلة، ومن ثم نسبة اثنين من المتغيرات المستقلة من نوع كاي-تربيع مقسومة على درجات حريتها. نظرًا لأن نسبة عادي وجذر متوسط المربعات لـ m من العاديين المستقلين لها توزيع t_m، فإن مربع متغير t_m له توزيع F على 1 و m درجات حرية.\n            <br/>\n            توزيع F غير المركزي هو مرة أخرى نسبة متوسط المربعات من العاديين المستقلين ذوي التباين الواحد، ولكن تلك في المقام يُسمح لها بأن تكون لها متوسطات غير صفرية و ncp هو مجموع مربعات المتوسطات. انظر كاي-تربيع لمزيد من التفاصيل حول التوزيعات غير المركزية.\n            <br/>\n            <br/><b>القيمة</b>\n            <br/>\n            df يعطي الكثافة، pf يعطي دالة التوزيع، qf يعطي دالة الكمية، و rf يولد انحرافات عشوائية.\n            <br/>\n            ستؤدي المعلمات غير الصالحة إلى قيمة إرجاع NaN، مع تحذير.\n            <br/>\n            يتم تحديد طول النتيجة بواسطة n لـ rf، وهو الحد الأقصى من أطوال المعلمات العددية للوظائف الأخرى.\n            <br/>\n            يتم إعادة تدوير المعلمات العددية بخلاف n إلى طول النتيجة. يتم استخدام العناصر الأولى فقط من المعلمات المنطقية.\n            <br/>\n            <br/><b>ملاحظة</b>\n            <br/>\n            توفير ncp = 0 يستخدم الخوارزمية لتوزيع غير المركزي، والتي ليست نفس الخوارزمية المستخدمة إذا تم حذف ncp. هذا لضمان سلوك متسق في الحالات القصوى مع قيم ncp قريبة جدًا من الصفر.\n            <br/>\n            الكود لـ ncp غير الصفري مخصص أساسًا للاستخدام للقيم المعتدلة من ncp: لن يكون دقيقًا للغاية، خاصة في الأطراف، للقيم الكبيرة."
  }
}