{
  "title": "حجم العينة، اختبار نسبة واحدة",
  "navigation": "نسبة واحدة",
  "howtouse": "حدد إما حجم العينة أو القوة، وسيتم حساب الآخر",
  "n": "حجم العينة",
  "power": "القوة (0-1)",
  "prop": "النسبة البديلة (0-1)",
  "prop0": "النسبة الصفرية (0-1)",
  "siglevel": "مستوى الدلالة (0-1)",
  "alternativeopt": "الفرضية البديلة",
  "twosided": "ذو جانبين",
  "onesided": "ذو جانب واحد",
  "help": {
    "title": "حجم العينة، اختبار نسبة واحدة",
    "r_help": "help(pnorm, package ='stats')",
    "body": "\nهذا تقييم لحجم العينة لاختبار نسبة عينة واحدة. يقوم بحساب حجم العينة أو القوة، عندما يحدد المستخدم أحدهما. يستخدم الحساب الصيغة الموجودة في Chow S، Shao J، Wang H. حسابات حجم العينة في البحث السريري (2008). يستخدم تقريبًا طبيعيًا مع الانحراف المعياري بناءً على النسبة البديلة.\n<br/><br/>\n<b>حجم العينة:</b> حدد عدد الموضوعات في الدراسة\n<br/><br/>\n<b>القوة:</b> حدد القوة المطلوبة للدراسة، أي احتمال أن يرفض الاختبار الفرضية الصفرية إذا كانت الفرضية البديلة صحيحة.\n<br/><br/>\n<b>النسبة البديلة (0-1):</b> حدد النسبة تحت الفرضية البديلة\n<br/><br/>\n<b>النسبة الصفرية (0-1):</b> حدد النسبة تحت الفرضية الصفرية\n<br/><br/>\n<b>مستوى الدلالة:</b> حدد مستوى الدلالة المطلوب (أي خطأ من النوع الأول) للاختبار\n<br/><br/>\n<b>الفرضية البديلة:</b> حدد ما إذا كان الاختبار ذو جانبين أو جانب واحد\n<br/><br/>\n<b>حزم R المطلوبة:</b> stats\n\t\t\t"
  }
}