{
  "title": "Generați automat detalii despre factor (dimensiune variabilă) pentru un studiu DoE",
  "navigation": "Detalii despre factor (dimensiune variabilă)",
  "datasetname": "Numele tabelului de detalii despre factor",
  "label1": "Detalii despre factor pentru factor1",
  "label2": "Detalii despre factor pentru factor2",
  "label3": "Detalii despre factor pentru factor3",
  "label4": "Detalii despre factor pentru factor4",
  "label5": "Detalii despre factor pentru factor5",
  "factor1": "Numele factorului1 (de exemplu, Piese, Operator, Mașină etc.)",
  "numOfFactorLevels1": "Numărul de niveluri pentru factor1",
  "factorLevels1": "Lăsați gol pentru a genera automat valori sau specificați valori - exemplu: -1, 1, 'string1', 2, 0",
  "prefixForfactorLevels1": "Dacă generați automat, specificați orice prefix. Dacă este gol, va crea valori ca 1,2,3,..",
  "factor2": "Numele factorului2 (de exemplu, Piese, Operator, Mașină etc.)",
  "numOfFactorLevels2": "Numărul de niveluri pentru factor2",
  "factorLevels2": "Lăsați gol pentru a genera automat valori sau specificați valori - exemplu: -1, 1, 'string1', 2, 0",
  "prefixForfactorLevels2": "Dacă generați automat, specificați orice prefix. Dacă este gol, va crea valori ca 1,2,3,..",
  "factor3": "Numele factorului3 (de exemplu, Piese, Operator, Mașină etc.)",
  "numOfFactorLevels3": "Numărul de niveluri pentru factor3",
  "factorLevels3": "Lăsați gol pentru a genera automat valori sau specificați valori - exemplu: -1, 1, 'string1', 2, 0",
  "prefixForfactorLevels3": "Dacă generați automat, specificați orice prefix. Dacă este gol, va crea valori ca 1,2,3,..",
  "factor4": "Numele factorului4 (de exemplu, Piese, Operator, Mașină etc.)",
  "numOfFactorLevels4": "Numărul de niveluri pentru factor4",
  "factorLevels4": "Lăsați gol pentru a genera automat valori sau specificați valori - exemplu: -1, 1, 'string1', 2, 0",
  "prefixForfactorLevels4": "Dacă generați automat, specificați orice prefix. Dacă este gol, va crea valori ca 1,2,3,..",
  "factor5": "Numele factorului5 (de exemplu, Piese, Operator, Mașină etc.)",
  "numOfFactorLevels5": "Numărul de niveluri pentru factor5",
  "factorLevels5": "Lăsați gol pentru a genera automat valori sau specificați valori - exemplu: -1, 1, 'string1', 2, 0",
  "prefixForfactorLevels5": "Dacă generați automat, specificați orice prefix. Dacă este gol, va crea valori ca 1,2,3,..",
  "autoFillChkbx": "Umpleți automat nivelurile",
  "help": {
    "title": "Generați automat detalii despre factor",
    "body": "\n\t\t\t\t<b>Descriere</b></br>\n\t\t\t\tFactorii pot avea dimensiuni variabile, adică fiecare factor poate avea un număr diferit de niveluri\n\t\t\t\tGenerați automat un tabel cu detalii despre factor pe baza parametrului specificat - numărul de factori și nivelurile maxime pentru factori împreună cu valorile implicite pentru factor care trebuie utilizate. Dacă se folosesc valori non-numerice pentru factor, specificați-le între ghilimele simple, de exemplu 1,-1,'name1',0,'string2'\n\t\t\t\t<br/>\n\t\t\t\t<br/>\n\t\t\t\tOdată ce detaliile despre factor sunt generate automat și tabelul de factori apare pe interfața UI a grilei de date, puteți schimba valorile și/sau elimina unele valori din grilă pentru a manipula tabelul așa cum doriți\n\t\t\t\t<br/>\n\t\t\t\t<br/>\n\t\t\t\tOdată ce tabelul de factori este gata, mergeți la DoE -> Meniul Creare Design pentru a crea un design din acest tabel de factori\n\t\t\t\t<br/>\n\t\t\t\t<br/>\n\t\t\t\tDacă numărul de factori este <= 26, factorii sunt denumiți cu litere mari ca A, B, C, .., altfel, denumiți ca F1, F2, ..., F27, F28, ..\n\t\t\t"
  }
}