{
  "r_editor_script": "Script editor R",
  "grid_edit": "Modifica griglia",
  "open_dataset": "Apri dataset",
  "outputWindow": {
    "main": {
      "new": "Aggiungi nuovo elemento all'output",
      "save": "Salva",
      "export": "Esporta output",
      "clear": "Pulisci output",
      "close": "Chiudi scheda output",
      "restart": "Riavvia R",
      "rerun": "Esegui di nuovo",
      "freeze": "Blocca intestazioni tabella",
      "toc": "Mostra indice"
    },
    "code": {
      "hide": "Nascondi codice",
      "undo": "Annulla",
      "redo": "Ripeti",
      "find": "Trova",
      "findNext": "Trova successivo",
      "findReplace": "Trova e sostituisci",
      "comment": "Commento",
      "uncomment": "Annulla commento",
      "launchDialog": "Apri dialogo",
      "showCode": "Mostra codice",
      "hideCode": "Nascondi codice",
      "revert": "Ripristina modifiche",
      "execute": "Esegui codice R"
    },
    "side": {
      "remove": "Rimuovi"
    }
  },
  "rEditorWindow": {
    "execute": "Esegui codice R",
    "undo": "Annulla",
    "redo": "Ripeti",
    "find": "Trova",
    "next": "Trova successivo",
    "replace": "Trova e sostituisci",
    "comment": "Commento",
    "uncomment": "Annulla commento",
    "save": "",
    "saveAs": "Salva come",
    "clear": "Pulisci o chiudi file",
    "toggle": "Attiva/disattiva editor R"
  },
  "dataGrid": {
    "add": "Crea un nuovo dataset",
    "refresh": "Aggiorna dataset",
    "undo": "Annulla modifiche",
    "redo": "Ripeti modifiche"
  },
  "REditrOutputContext": {
    "execute": "Eseguire",
    "executeAll": "Esegui tutto",
    "find": "Trova",
    "next": "Trova successivo",
    "replace": "Trova e sostituisci",
    "cut": "Taglia",
    "copy": "Copia",
    "paste": "Incolla",
    "comment": "Commento",
    "uncomment": "Annulla commento",
    "selectAll": "Seleziona tutto"
  },
  "CntxInsDrowAbv": "Inserisci riga dati sopra",
  "CntxinsDrowBelow": "Inserisci riga dati sotto",
  "CntxDeleteRow": "Elimina riga",
  "CntxAddFacLvl": "Aggiungi livello fattore",
  "CntxMkFac": "Crea fattore",
  "CntxMkOrdFac": "Crea fattore ordinato",
  "CntxMkChar": "Crea carattere",
  "CntxMkNum": "Crea numerico",
  "CntxMkNumEU": "Converti in numerico (Europeo)",
  "CntxInsDtVar": "Inserisci nuova variabile data",
  "CntxInsDtVarEnd": "Inserisci nuova variabile data alla fine",
  "CntxInsDtTmVar": "Inserisci nuova variabile data e ora",
  "CntxInsDtTmVarEnd": "Inserisci nuova variabile data e ora alla fine",
  "CntxInsNumVar": "Inserisci nuova variabile numerica",
  "CntxInsNumVarEnd": "Inserisci nuova variabile numerica alla fine",
  "CntxInsCharVar": "Inserisci nuova variabile carattere",
  "CntxInsCharVarEnd": "Inserisci nuova variabile carattere alla fine",
  "CntxInsFacVar": "Inserisci nuova variabile fattore",
  "CntxInsFacVarEnd": "Inserisci nuova variabile fattore alla fine",
  "CntxDelCol": "Elimina colonna",
  "CntxDelVar": "Elimina variabile",
  "CntxMkTopRowHdr": "Trasforma la riga superiore in un'intestazione",
  "CntxCopy": "Copia",
  "CntxPaste": "Incolla",
  "RenOutputTitle": "Cambia titolo della scheda di output",
  "RenOutputOldname": "Titolo corrente",
  "RenOutputNewname": "Nuovo titolo",
  "RenOutputCancelBtn": "Annulla",
  "RenOutputRenameBtn": "Rinomina",
  "exportFileLockedOk": "Ok",
  "viewModeSplashTitle": "Attenzione! Solo modalità di visualizzazione",
  "viewModeSplashMsg": "Questa applicazione è solo in modalità di visualizzazione. Non puoi eseguire alcuna analisi. Puoi solo visualizzare le vecchie analisi all'interno di un progetto o di un file .bmd. Se hai bisogno della piena funzionalità, ottieni una licenza software per questa applicazione.",
  "chatAttachmentInitialMessage": "Interpreta i risultati della mia analisi"  
}