{
  "title": "創建常規（分數）因子2級設計",
  "navigation": "創建常規（分數）因子2級設計",
  "selectedvars": "選擇變數",
  "datasetname": "設計名稱",
  "lblheading": "大小和隨機化",
  "numOfRuns": "運行次數（如果指定，必須是2的幂，否則設為0）",
  "numOfBlocks": "區塊數",
  "alias2FIsChk": "區塊可能與2fis混淆",
  "numOfCenterPts": "中心點數量（如果使用，至少要有2個）",
  "centerPointDistribution": "中心點分布的位置數量（大於1）",
  "replications": "重複",
  "repeatOnlyChk": "僅重複",
  "lbl1": "您可能不需要更改隨機化設置",
  "randomseeds": "隨機化的種子",
  "randomizationChk": "隨機生成設計",
  "lbl2": "注意：僅影響MaxC2選擇或未指定的運行次數的設計生成",
  "lbldesignheading": "設計屬性",
  "roman": "最小分辨率（III，IV，V...）",
  "marad": "MA（最大分辨率和最小偏差）",
  "maxC2rad": "MaxC2（最大清晰2fis的數量）",
  "lbl3": "指定設計目錄（可選）",
  "designChk": "使用目錄中的設計",
  "designcatlgname": "設計目錄名稱，例如catlg",
  "designnamefromcatlg": "來自設計目錄的設計名稱",
  "nrunsChk": "自動計算上述指定設計的運行次數",
  "help": {
    "title": "創建常規（分數）因子2級設計",
    "r_help": "幫助(FrF2, 包 = FrF2)",
    "body": "\n\t\t\t\t<b>描述</b></br>\n\t\t\t\tFrF2函數生成常規分數因子2級設計\n\t\t\t\t<br/>\n\t\t\t\t<br/>\n\t\t\t\t有關詳細幫助 - 使用R幫助(FrF2, 包 = FrF2)\n\t\t\t\t<br/>\n\t\t\t\t<br/>\n\t\t\t\t使用菜單DOE->檢查設計->檢查FrF2目錄瀏覽可用的FrF2設計，從FrF2包中加載的設計目錄中引用\n\t\t\t\t<br/>\n\t\t\t\t<br/>\n\t\t\t\t要嘗試此操作，您可以使用名為factor_grid_Injection Molding FrF2.xlsx的示例數據集文件。通過文件打開菜單在數據網格中打開文件\n\t\t\t\t<br/>\n\t\t\t"
  }
}