{
  "title": "擴展權重",
  "navigation": "擴展",
  "datasetname": "擴展權重的數據集名稱",
  "destination": "輸入包含權重的列",
  "help": {
    "title": "擴展權重",
    "r_help": "help(expandRows, package=splitstackshape)",
    "body": "<b>描述</b></br>\n        創建一個新的數據集，根據權重擴展行。根據源數據框或數據表中某一列的值擴展（複製）數據框的行。BSkySetWeights() 調用來自 splitstackshape 包的 expandRows()。\n        <br/>\n        <b>用法</b>\n        <br/>\n             <code> \n        BSkySetWeight(weights, data, newdata)\n        </code> <br/>\n          <b>參數</b><br/>\n         <ul>\n           <li>\n        weights: 包含權重的數據集變量。 \n        </li>\n        <li>\n        data: 輸入的數據框或數據表。\n        </li>\n        <li>\n        newdata: 根據指定的權重複製行的新數據集。\n        </li>\n        </ul>\n        <b>包</b></br>\n        splitstackshape</br>\n        <b>幫助</b></br>\n        help (expandRows)\n        "
  }
}