{
  "title": "样本大小，ANOVA",
  "navigation": "ANOVA",
  "howtouse": "计算样本大小：指定组均值和功效\n计算功效：指定样本大小和组均值\n计算组均值的可检测方差：指定样本大小和功效",
  "numgrps": "组数",
  "n": "每组样本大小",
  "grpmeans": "组均值，指定为用逗号分隔的值，例如 20, 25, 40",
  "power": "功效 (0-1)",
  "sd": "标准差",
  "siglevel": "显著性水平 (0-1)",
  "help": {
    "title": "样本大小，ANOVA",
    "r_help": "help(power.anova.test, package ='stats')",
    "body": "\n这是对平衡单因素ANOVA的样本大小评估。它计算样本大小、功效或均值差异（计算为均值之间的方差），当用户指定其他两个时。\n<br/><br/>\n<b>组数：</b>指定研究中的组数\n<br/><br/>\n<b>每组样本大小：</b>指定每组中的受试者数量\n<br/><br/>\n<b>组均值：</b>指定您希望能够检测到的每组的均值。至少有一个均值必须与其他均值不同。\n<br/><br/>\n<b>功效：</b>指定研究的期望功效，即如果替代假设为真，测试拒绝零假设的概率。\n<br/><br/>\n<b>标准差：</b>指定结果的标准差。假设在各组之间是相同的。\n<br/><br/>\n<b>显著性水平：</b>指定测试的期望显著性水平（即第一类错误）\n<br/><br/>\n<b>所需的R包：</b>stats\n\t\t\t"
  }
}