{
  "title": "Analiza Discriminantă",
  "navigation": "Discriminant",
  "modelname": "Numele modelului",
  "tvarbox1": "Variabile dependente",
  "tvarbox2": "Factor fix",
  "blockVar": "Covariate",
  "testStatistic": "Statistică de test",
  "label2": "Opțiuni pentru post-hocs",
  "combon": "Compară mediile folosind:",
  "emm": "Mediile marginale estimate",
  "displayBoxMDetails": "Afișează detalii asociate cu testul Box's M (Notă: Rezultatele testului Box's M sunt întotdeauna afișate)",
  "adjust": "Metodă de ajustare a valorilor p",
  "levenesTest": "Testul Levene",
  "posthocs": "Post-hocs",
  "plotMeansCI": "Grafic al mediilor și intervalelor de încredere",
  "help": {
    "title": "Analiza Discriminantă",
    "r_help": "ajutor(manova, pachet='stats')",
    "body": "\n<b>Descriere</b></br>\nAnaliza Discriminantă: Se oferă teste multivariate omnibus și valorile F și p corespunzătoare. De asemenea, sunt furnizate teste univariate de urmărire.</br> NOTĂ: În prezent, susținem un singur factor independent</br>\nNOTĂ: Nu afișăm intervalul de încredere în graficul mediilor, deoarece sunt afișate avertismente inutile. Colaborăm cu autorul pachetului gplots pentru a rectifica acest lucru.</br>\n<br/>\n<b>Utilizare</b>\n<br/>\n<code> \nmanova(...)</br>\nmanova(data = dataset1, cbind(var1,var2...) ~ factor1  )\n</code> <br/>\n<b>Argumente</b><br/>\n<ul>\n<li>\n...: Argumente transmise la aov\n</li>\n</ul>\n<b>Detalii</b></br>\nClasa \"manova\" diferă de clasa \"aov\" în selectarea unei metode de rezumat diferite. Funcția manova apelează aov și apoi adaugă clasa \"manova\" la obiectul rezultat pentru fiecare strat.​</br>\n<b>Valoare</b><br/>\nConsultați ajutorul aov, detalii mai jos<br/>\n<b>Pachet</b></br>\nstats</br>\n<b>Ajutor</b></br>\nFaceți clic pe butonul Ajutor R pentru a obține ajutor detaliat R.</br> De asemenea, puteți introduce help(manova, package ='stats') și apăsa CTRL Enter în editorul de sintaxă R pentru a obține ajutor</br>\n"
  }
}