{
    "title": "Kreuztabelle",
    "navigation": "Kreuztabelle (Veraltet)",
    "row": "Zeilenvariable",
    "column": "Spaltenvariable",
    "layer": "Schichtvariable(n)",
    "weight": "Gewicht (einzeln)",
    "label1": "Statistiken",
    "chisq": "Chi-Quadrat",
    "mcnemar": "McNemar",
    "fisher": "Fisher",
    "label2": "Residuen",
    "unstandardized": "Unstandardisiert",
    "standardized": "Standardisiert",
    "adjusted": "Angepasst",
    "label3": "Prozentwerte",
    "rowpercent": "Zeile",
    "colpercent": "Spalte",
    "label4": "Zählungen",
    "expected": "Erwartet",
    "label5": "Langformat der Tabelle",
    "longTbl": "Lange Tabelle",
    "help": {
        "title": "Kreuztabelle",
        "r_help": "help(CrossTable, package=gmodels)",
        "body": "<b>Beschreibung</b></br>\nErstellt eine Kreuztabelle mit Zeilen-, Spalten- und Schichtvariablen und zeigt optional folgendes an:<br/>\nErwartete Zählungen<br/>\nZeilen- und Spaltenprozentsätze<br/>\nUnstandardisierte, standardisierte und angepasste Residuen<br/>\nChi-Quadrat mit Odds Ratio, McNemar- und Fisher-Statistiken<br/>\n<br/>\n<b>Verwendung</b>\n<br/>\n<code>\nBSkyCrossTable(x,y,schichten, gewicht, datensatzname, chisq= FALSCH, prop.r=FALSCH, prop.c=FALSCH, resid=FALSCH, sresid=FALSCH, expected=FALSCH, asresid=FALSCH)\n</code><br/>\n<b>Argumente</b><br/>\n<ul>\n<li>x: Zeilenvariable</li>\n<li>y: Spaltenvariable</li>\n<li>schichten: eine oder mehrere Schichtvariablen</li>\n<li>gewicht: eine numerische Variable mit Häufigkeitsgewichten</li>\n<li>datensatzname: Name des Datensatzes, aus dem x, y und Schichten (Variablen) ausgewählt werden</li>\n<li>chisq: wenn WAHR, wird eine Chi-Quadrat-Tabelle erzeugt</li>\n<li>prop.r: Wenn dies WAHR ist, werden Zeilenprozentsätze erzeugt</li>\n<li>prop.c: Wenn dies WAHR ist, werden Spaltenprozentsätze erzeugt</li>\n<li>resid: Wenn dies WAHR ist, werden unstandardisierte Residuen erzeugt</li>\n<li>sresid: Wenn dies WAHR ist, werden standardisierte Residuen erzeugt</li>\n<li>expected: Wenn dies WAHR ist, werden erwartete Zählungen erzeugt</li>\n<li>asresid: Wenn dies WAHR ist, werden angepasste Residuen erzeugt</li>\n</ul>\n<b>Ergebnis</b><br/>Eine Liste mit den Ergebnissen<br/>\n<b>Beispiel</b><br/>\n<code>\nBSky_Multiway_Cross_Tab = BSkyCrossTable(x=c('Hersteller'),y=c('Modell'),<br/>\nschichten=c('Typ'),datensatzname='Dataset2',<br/>\nchisq = FALSCH,prop.r=FALSCH,prop.c=FALSCH,<br/>\nresid=FALSCH,sresid=FALSCH,expected=FALSCH,<br/>\nasresid=FALSCH)<br/>\nBSkyFormat(BSky_Multiway_Cross_Tab)</code><br/>\n<b>Paket</b><br/>gmodels<br/>\n<b>Hilfe</b><br/>Für detaillierte Hilfe klicken Sie auf das R-Symbol oben rechts in diesem Dialogfeld oder führen Sie den folgenden Befehl aus: Hilfe(CrossTable, Paket=gmodels) und erstellen Sie einen R-Code-Block, indem Sie auf + im Ausgabefenster klicken\n"
        }
}
